nester.py
titascodes_nester-1.2.0.dist-info/METADATA
titascodes_nester-1.2.0.dist-info/WHEEL
titascodes_nester-1.2.0.dist-info/top_level.txt
titascodes_nester-1.2.0.dist-info/RECORD
