Metadata-Version: 2.4
Name: titascodes-nester
Version: 1.2.0
Summary: nested lists printer
Home-page: http://www.titasraman.com
Author: titascodes
Author-email: titas.r@outlook.com
Dynamic: author
Dynamic: author-email
Dynamic: home-page
Dynamic: summary
